polarsmeteorological-0.34.19.dist-info/METADATA
polarsmeteorological-0.34.19.dist-info/WHEEL
polarsmeteorological/utils.py
polarsmeteorological/__pycache__/__init__.cpython-312.pyc
polarsmeteorological/__pycache__/utils.cpython-312.pyc
polarsmeteorological/__pycache__/namespace.cpython-312.pyc
polarsmeteorological/__pycache__/functions.cpython-312.pyc
polarsmeteorological/__init__.py
polarsmeteorological/functions.py
polarsmeteorological/namespace.py
polarsmeteorological/_internal.pyi
polarsmeteorological/polarsmeteorological.pypy310-pp73-x86_64-linux-gnu.so
polarsmeteorological-0.34.19.dist-info/RECORD
