Metadata-Version: 2.3
Name: polarsmeteorological
Version: 0.34.19
